{
  "version": "1.0.1",
  "characters": [
    { "word": "Moses", "hints": ["burning", "staff", "sea"] },
    { "word": "David", "hints": ["giant", "stone", "king"] },
    { "word": "Solomon", "hints": ["wisdom", "temple", "judgment"] },
    { "word": "Elijah", "hints": ["fire", "prophet", "mountain"] },
    { "word": "Abraham", "hints": ["promise", "journey", "stars"] },
    { "word": "Joseph", "hints": ["dreams", "coat", "Egypt"] },
    { "word": "Daniel", "hints": ["lions", "vision", "kingdom"] },
    { "word": "Peter", "hints": ["rock", "denial", "water"] },
    { "word": "Paul", "hints": ["letters", "journey", "chains"] },
    { "word": "John", "hints": ["light", "word", "vision"] },
    { "word": "Mary", "hints": ["mother", "promise", "birth"] },
    { "word": "Esther", "hints": ["queen", "risk", "silence"] },
    { "word": "Ruth", "hints": ["loyalty", "fields", "stay"] },
    { "word": "Samson", "hints": ["strength", "hair", "fall"] },
    { "word": "Gideon", "hints": ["few", "battle", "fear"] },
    { "word": "Joshua", "hints": ["walls", "trumpet", "land"] },
    { "word": "Isaiah", "hints": ["vision", "prophecy", "future"] },
    { "word": "Jeremiah", "hints": ["tears", "warning", "burden"] },
    { "word": "Ezekiel", "hints": ["bones", "vision", "spirit"] },
    { "word": "Noah", "hints": ["rain", "ark", "animals"] },
    { "word": "Adam", "hints": ["first", "garden", "dust"] },
    { "word": "Eve", "hints": ["fruit", "choice", "beginning"] },
    { "word": "Cain", "hints": ["brother", "mark", "field"] },
    { "word": "Abel", "hints": ["offering", "shepherd", "early"] },
    { "word": "Jacob", "hints": ["ladder", "wrestle", "name"] },
    { "word": "Isaac", "hints": ["son", "altar", "promise"] },
    { "word": "Sarah", "hints": ["laughter", "child", "age"] },
    { "word": "Rebecca", "hints": ["choice", "journey", "twins"] },
    { "word": "Deborah", "hints": ["judge", "leader", "battle"] },
    { "word": "Jonah", "hints": ["run", "fish", "return"] },
	{ "word": "Aaron", "hints": ["priest", "brother", "rod"] },
	{ "word": "Joshua", "hints": ["leader", "land", "successor"] },
	{ "word": "Caleb", "hints": ["spy", "faithful", "strong"] },
	{ "word": "Samuel", "hints": ["prophet", "call", "judge"] },
	{ "word": "Saul", "hints": ["first", "king", "fall"] },
	{ "word": "Nathan", "hints": ["prophet", "rebuke", "king"] },
	{ "word": "Bathsheba", "hints": ["woman", "king", "son"] },
	{ "word": "Solomon", "hints": ["wisdom", "temple", "rich"] },
	{ "word": "Rehoboam", "hints": ["king", "division", "son"] },
	{ "word": "Jeroboam", "hints": ["king", "idols", "split"] },
	{ "word": "Ahab", "hints": ["king", "evil", "queen"] },
	{ "word": "Jezebel", "hints": ["queen", "idol", "wicked"] },
	{ "word": "Elisha", "hints": ["prophet", "double", "miracles"] },
	{ "word": "Naaman", "hints": ["leprosy", "river", "healed"] },
	{ "word": "Hezekiah", "hints": ["king", "prayer", "healed"] },
	{ "word": "Josiah", "hints": ["king", "law", "reform"] },
	{ "word": "Ezra", "hints": ["scribe", "law", "return"] },
	{ "word": "Nehemiah", "hints": ["wall", "builder", "leader"] },
	{ "word": "Job", "hints": ["suffering", "faith", "patience"] },
	{ "word": "Zechariah", "hints": ["priest", "vision", "angel"] },
	{ "word": "Elizabeth", "hints": ["mother", "old", "joy"] },
	{ "word": "John the Baptist", "hints": ["prepare", "water", "voice"] },
	{ "word": "Herod", "hints": ["king", "fear", "order"] },
	{ "word": "Pilate", "hints": ["judge", "wash", "decision"] },
	{ "word": "Thomas", "hints": ["doubt", "see", "believe"] },
	{ "word": "Matthew", "hints": ["tax", "disciple", "gospel"] },
	{ "word": "Barnabas", "hints": ["encourage", "helper", "mission"] },
	{ "word": "Timothy", "hints": ["young", "leader", "letter"] },
	{ "word": "Titus", "hints": ["pastor", "order", "letter"] },
	{ "word": "Stephen", "hints": ["stones", "first", "martyr"] }
  ],
  "objects": [
    { "word": "Ark of the Covenant", "hints": ["presence", "gold", "carried"] },
    { "word": "Staff of Moses", "hints": ["wood", "power", "sign"] },
    { "word": "David's Sling", "hints": ["stone", "string", "strike"] },
    { "word": "Ten Commandments", "hints": ["law", "stone", "ten"] },
    { "word": "Crown of Thorns", "hints": ["pain", "head", "mockery"] },
    { "word": "Noah's Ark", "hints": ["wood", "animals", "flood"] },
    { "word": "Burning Bush", "hints": ["fire", "voice", "desert"] },
    { "word": "Golden Calf", "hints": ["idol", "gold", "worship"] },
    { "word": "Manna", "hints": ["bread", "daily", "desert"] },
    { "word": "Goliath's Sword", "hints": ["giant", "weapon", "victory"] },
    { "word": "Tablets of Stone", "hints": ["law", "engraved", "mountain"] },
    { "word": "Urim and Thummim", "hints": ["priest", "decision", "mystery"] },
    { "word": "Menorah", "hints": ["light", "lamp", "temple"] },
    { "word": "Bread of Life", "hints": ["food", "spirit", "life"] },
    { "word": "Alabaster Jar", "hints": ["perfume", "break", "costly"] },
    { "word": "Scroll", "hints": ["writing", "roll", "ancient"] },
    { "word": "Phylactery", "hints": ["law", "wear", "memory"] },
    { "word": "Temple Veil", "hints": ["barrier", "tear", "holy"] },
	{ "word": "Bronze Serpent", "hints": ["pole", "look", "heal"] },
	{ "word": "Altar", "hints": ["sacrifice", "fire", "offer"] },
	{ "word": "Trumpet", "hints": ["sound", "signal", "battle"] },
	{ "word": "Incense", "hints": ["smell", "prayer", "burn"] },
	{ "word": "Lampstand", "hints": ["light", "stand", "oil"] },
	{ "word": "Shepherd's Rod", "hints": ["guide", "sheep", "staff"] },
	{ "word": "Censer", "hints": ["smoke", "priest", "burn"] },
	{ "word": "Tent of Meeting", "hints": ["presence", "meeting", "holy"] },
	{ "word": "Purple Robe", "hints": ["mock", "king", "wear"] },
	{ "word": "Thirty Coins", "hints": ["silver", "betray", "price"] },
	{ "word": "Net", "hints": ["fish", "catch", "water"] },
	{ "word": "Oil Jar", "hints": ["pour", "multiply", "need"] },
	{ "word": "Bread Loaves", "hints": ["food", "multiply", "crowd"] },
	{ "word": "Cup", "hints": ["drink", "blood", "symbol"] },
	{ "word": "Cross", "hints": ["wood", "death", "save"] },
	{ "word": "Stone Tomb", "hints": ["grave", "sealed", "empty"] },
	{ "word": "White Garment", "hints": ["clean", "pure", "wear"] },
	{ "word": "Fishing Boat", "hints": ["water", "work", "disciples"] },
	{ "word": "Chains", "hints": ["bound", "prison", "hold"] },
	{ "word": "Scroll of Life", "hints": ["names", "heaven", "record"] }
  ],
  "places": [
    { "word": "Jerusalem", "hints": ["city", "temple", "center"] },
    { "word": "Egypt", "hints": ["slavery", "river", "power"] },
    { "word": "Bethlehem", "hints": ["birth", "small", "town"] },
    { "word": "Nazareth", "hints": ["home", "quiet", "origin"] },
    { "word": "Galilee", "hints": ["region", "water", "teaching"] },
    { "word": "Sinai", "hints": ["mountain", "law", "fire"] },
    { "word": "Jericho", "hints": ["walls", "fall", "sound"] },
    { "word": "Babylon", "hints": ["exile", "empire", "captivity"] },
    { "word": "Garden of Eden", "hints": ["beginning", "fruit", "loss"] },
    { "word": "Mount Carmel", "hints": ["prophet", "fire", "challenge"] },
    { "word": "Dead Sea", "hints": ["salt", "still", "lifeless"] },
    { "word": "Sea of Galilee", "hints": ["water", "storm", "boat"] },
    { "word": "Jordan River", "hints": ["water", "crossing", "baptism"] },
    { "word": "Gethsemane", "hints": ["garden", "prayer", "night"] },
    { "word": "Golgotha", "hints": ["hill", "cross", "death"] },
    { "word": "Canaan", "hints": ["land", "promise", "inheritance"] },
    { "word": "Nineveh", "hints": ["city", "repent", "warning"] },
    { "word": "Antioch", "hints": ["church", "name", "beginning"] },
    { "word": "Rome", "hints": ["empire", "power", "rule"] },
    { "word": "Ephesus", "hints": ["city", "letter", "warning"] },
    { "word": "Corinth", "hints": ["church", "problems", "teaching"] },
    { "word": "Athens", "hints": ["philosophy", "debate", "altar"] },
	{ "word": "Hebron", "hints": ["city", "burial", "promise"] },
	{ "word": "Bethel", "hints": ["dream", "ladder", "place"] },
	{ "word": "Shiloh", "hints": ["tabernacle", "worship", "early"] },
	{ "word": "Samaria", "hints": ["region", "mixed", "well"] },
	{ "word": "Damascus", "hints": ["road", "light", "change"] },
	{ "word": "Caesarea", "hints": ["city", "sea", "Roman"] },
	{ "word": "Patmos", "hints": ["island", "vision", "exile"] },
	{ "word": "Philippi", "hints": ["city", "jail", "joy"] },
	{ "word": "Thessalonica", "hints": ["church", "letters", "hope"] },
	{ "word": "Laodicea", "hints": ["lukewarm", "church", "warning"] },
	{ "word": "Pergamum", "hints": ["church", "altar", "faith"] },
	{ "word": "Smyrna", "hints": ["church", "suffering", "faithful"] },
	{ "word": "Tyre", "hints": ["coast", "trade", "city"] },
	{ "word": "Sidon", "hints": ["city", "coast", "region"] },
	{ "word": "Beersheba", "hints": ["well", "oath", "south"] },
	{ "word": "Mount Zion", "hints": ["hill", "city", "holy"] },
	{ "word": "Mount Horeb", "hints": ["mountain", "fire", "law"] },
	{ "word": "Kidron Valley", "hints": ["valley", "crossing", "dark"] },
	{ "word": "Bethany", "hints": ["home", "friends", "near"] },
	{ "word": "Emmaus", "hints": ["road", "walk", "recognize"] }
  ],
  "events": [
    { "word": "The Exodus", "hints": ["escape", "journey", "freedom"] },
    { "word": "The Flood", "hints": ["rain", "water", "reset"] },
    { "word": "The Creation", "hints": ["beginning", "order", "world"] },
    { "word": "The Crucifixion", "hints": ["cross", "death", "sacrifice"] },
    { "word": "The Resurrection", "hints": ["life", "return", "empty"] },
    { "word": "The Last Supper", "hints": ["meal", "bread", "betrayal"] },
    { "word": "The Baptism of Jesus", "hints": ["water", "spirit", "start"] },
    { "word": "The Transfiguration", "hints": ["light", "change", "mountain"] },
    { "word": "The Fall of Jericho", "hints": ["walls", "sound", "collapse"] },
    { "word": "The Parting of the Red Sea", "hints": ["water", "path", "escape"] },
    { "word": "Pentecost", "hints": ["fire", "tongues", "spirit"] },
    { "word": "The Birth of Jesus", "hints": ["child", "night", "arrival"] },
    { "word": "The Ascension", "hints": ["rise", "cloud", "departure"] },
    { "word": "Daniel in the Lion's Den", "hints": ["lions", "faith", "survive"] },
    { "word": "Jonah and the Whale", "hints": ["fish", "inside", "return"] },
    { "word": "David and Goliath", "hints": ["small", "giant", "victory"] },
    { "word": "The Plagues of Egypt", "hints": ["signs", "pain", "release"] },
    { "word": "The Tower of Babel", "hints": ["tower", "language", "scatter"] },
    { "word": "The Wedding at Cana", "hints": ["water", "wine", "beginning"] },
    { "word": "The Sermon on the Mount", "hints": ["teaching", "crowd", "hill"] },
	{ "word": "The Call of Abraham", "hints": ["leave", "promise", "journey"] },
	{ "word": "Jacob's Dream", "hints": ["ladder", "sleep", "vision"] },
	{ "word": "Joseph Sold", "hints": ["brothers", "betray", "silver"] },
	{ "word": "Burning Bush Encounter", "hints": ["fire", "voice", "call"] },
	{ "word": "Water from the Rock", "hints": ["strike", "thirst", "flow"] },
	{ "word": "Golden Calf Incident", "hints": ["idol", "anger", "break"] },
	{ "word": "Crossing Jordan", "hints": ["river", "stop", "pass"] },
	{ "word": "Calling of Samuel", "hints": ["voice", "night", "answer"] },
	{ "word": "David Anointed", "hints": ["oil", "chosen", "young"] },
	{ "word": "Fire on Mount Carmel", "hints": ["altar", "answer", "power"] },
	{ "word": "Healing of Naaman", "hints": ["wash", "river", "clean"] },
	{ "word": "Writing on the Wall", "hints": ["hand", "message", "doom"] },
	{ "word": "Birth of John", "hints": ["promise", "joy", "prepare"] },
	{ "word": "Calling of Disciples", "hints": ["follow", "leave", "nets"] },
	{ "word": "Calming the Storm", "hints": ["wind", "peace", "sea"] },
	{ "word": "Feeding the 5000", "hints": ["bread", "fish", "crowd"] },
	{ "word": "Walking on Water", "hints": ["sea", "faith", "step"] },
	{ "word": "Raising Lazarus", "hints": ["dead", "call", "alive"] },
	{ "word": "Trial of Jesus", "hints": ["judge", "crowd", "decision"] },
	{ "word": "Great Commission", "hints": ["go", "teach", "world"] }
  ],
  "books": [
    { "word": "Genesis", "hints": ["start", "origin", "creation"] },
    { "word": "Exodus", "hints": ["leave", "journey", "freedom"] },
    { "word": "Psalms", "hints": ["songs", "praise", "emotion"] },
    { "word": "Proverbs", "hints": ["wisdom", "short", "truth"] },
    { "word": "Isaiah", "hints": ["prophet", "vision", "future"] },
    { "word": "Matthew", "hints": ["gospel", "king", "account"] },
    { "word": "Mark", "hints": ["gospel", "action", "fast"] },
    { "word": "Luke", "hints": ["gospel", "detail", "order"] },
    { "word": "John", "hints": ["gospel", "light", "meaning"] },
    { "word": "Acts", "hints": ["church", "spread", "beginning"] },
    { "word": "Romans", "hints": ["letter", "logic", "faith"] },
    { "word": "Revelation", "hints": ["vision", "end", "symbols"] },
    { "word": "Daniel", "hints": ["dreams", "kingdoms", "visions"] },
    { "word": "Esther", "hints": ["queen", "courage", "hidden"] },
    { "word": "Ruth", "hints": ["loyalty", "story", "family"] },
    { "word": "Job", "hints": ["suffering", "questions", "faith"] },
    { "word": "Jonah", "hints": ["run", "fish", "lesson"] },
    { "word": "Hebrews", "hints": ["faith", "past", "greater"] },
    { "word": "James", "hints": ["works", "action", "truth"] },
    { "word": "Philippians", "hints": ["joy", "chains", "strength"] },
	{ "word": "Leviticus", "hints": ["law", "priest", "rules"] },
	{ "word": "Numbers", "hints": ["count", "journey", "people"] },
	{ "word": "Deuteronomy", "hints": ["repeat", "law", "speech"] },
	{ "word": "Joshua", "hints": ["land", "conquer", "leader"] },
	{ "word": "Judges", "hints": ["cycle", "leaders", "rescue"] },
	{ "word": "1 Samuel", "hints": ["king", "prophet", "start"] },
	{ "word": "2 Samuel", "hints": ["king", "David", "rule"] },
	{ "word": "1 Kings", "hints": ["kingdom", "split", "rule"] },
	{ "word": "2 Kings", "hints": ["fall", "exile", "end"] },
	{ "word": "1 Chronicles", "hints": ["history", "genealogy", "record"] },
	{ "word": "2 Chronicles", "hints": ["kings", "temple", "history"] },
	{ "word": "Ezra", "hints": ["return", "law", "restore"] },
	{ "word": "Nehemiah", "hints": ["wall", "rebuild", "leader"] },
	{ "word": "Ecclesiastes", "hints": ["meaning", "life", "vanity"] },
	{ "word": "Song of Songs", "hints": ["love", "poetry", "romance"] },
	{ "word": "Lamentations", "hints": ["cry", "loss", "grief"] },
	{ "word": "Ezekiel", "hints": ["vision", "prophet", "symbols"] },
	{ "word": "Hosea", "hints": ["love", "faithful", "story"] },
	{ "word": "Amos", "hints": ["justice", "warning", "prophet"] },
	{ "word": "Micah", "hints": ["justice", "humble", "walk"] }
  ]
}
